<?xml version="1.0" encoding="utf-8"?>
<BookingCommitRequest xmlns:xsi="http://www.w3.org/2001/XMLSchema-instance" xmlns:xsd="http://www.w3.org/2001/XMLSchema">
  <ContractVersion>0</ContractVersion>
  <Signature>zDUhFByDvds=|TUknsE4z+vWQdyW7fruA1HN14KYAQa1V8abqtLLa0AhHcqJ76kVxI4sgouzKystbAF1sCCvo1tsECYnLS94uy+VLuQHCCfe4LtWysjSVvoWpxZX2M6QSFeZr+Y6NHlFKfeJpGemGhJ4=</Signature>
  <BookingCommitRequestData>
    <State>New</State>
    <CurrencyCode>INR</CurrencyCode>
    <PaxCount>1</PaxCount>
    <BookingID>0</BookingID>
    <BookingParentID>0</BookingParentID>
    <SourcePOS>
      <State>New</State>
      <DomainCode>WWWW</DomainCode>
      <LocationCode>WWW</LocationCode>
    </SourcePOS>
    <BookingHold>
      <State>New</State>
      <HoldDateTime>2017-12-15T14:07:53.0810848+05:30</HoldDateTime>
    </BookingHold>
    <Passengers>
      <Passenger>
        <State>Modified</State>
        <PassengerNumber>0</PassengerNumber>
        <FamilyNumber>0</FamilyNumber>
        <Names>
          <BookingName>
            <State>New</State>
            <FirstName>Satyam</FirstName>
            <LastName>Prajapati</LastName>
            <Title>Mr</Title>
          </BookingName>
        </Names>
        <PassengerID>0</PassengerID>
        <PassengerInfos>
          <PassengerInfo>
            <State>New</State>
            <BalanceDue>0</BalanceDue>
            <Gender>Male</Gender>
            <TotalCost>0</TotalCost>
            <WeightCategory>Male</WeightCategory>
          </PassengerInfo>
        </PassengerInfos>
        <PseudoPassenger>false</PseudoPassenger>
      </Passenger>
    </Passengers>
    <BookingComments>
      <BookingComment>
        <State>New</State>
        <CommentType>Default</CommentType>
        <CommentText>NON-SOD-Confirm| 00105189| PRADEEP SHAH| Senior General Manager - Reservations| Reservation| 9873004088| satyam.tek@gmail.com</CommentText>
        <CreatedDate>0001-01-01T00:00:00</CreatedDate>
      </BookingComment>
    </BookingComments>
    <BookingContacts>
      <BookingContact>
        <State>New</State>
        <TypeCode>P</TypeCode>
        <Names>
          <BookingName>
            <State>New</State>
            <FirstName>PRADEEP</FirstName>
            <LastName>SHAH</LastName>
            <Title>Mr</Title>
          </BookingName>
        </Names>
        <EmailAddress>satyam.tek@gmail.com</EmailAddress>
        <HomePhone>9873004088</HomePhone>
        <CompanyName>SpiceJet</CompanyName>
        <AddressLine1>SpiceJet Ltd.| 319 | Udyog Vihar | Phase IV</AddressLine1>
        <City>Gurgaon - 122016</City>
        <ProvinceState>HR</ProvinceState>
        <PostalCode />
        <CountryCode>IN</CountryCode>
        <DistributionOption>Email</DistributionOption>
        <NotificationPreference>None</NotificationPreference>
      </BookingContact>
    </BookingContacts>
    <RestrictionOverride>false</RestrictionOverride>
    <ChangeHoldDateTime>true</ChangeHoldDateTime>
    <WaiveNameChangeFee>false</WaiveNameChangeFee>
    <WaivePenaltyFee>false</WaivePenaltyFee>
    <WaiveSpoilageFee>false</WaiveSpoilageFee>
    <DistributeToContacts>false</DistributeToContacts>
  </BookingCommitRequestData>
</BookingCommitRequest>