<?xml version="1.0" encoding="utf-8"?>
<PriceItineraryRequest xmlns:xsi="http://www.w3.org/2001/XMLSchema-instance" xmlns:xsd="http://www.w3.org/2001/XMLSchema">
  <ContractVersion>0</ContractVersion>
  <Signature>VfsO/bFLW2Q=|6HHp9tKUsOScBBZRfb66U1KtKOYtxrEeJU5XW5UlKE56ngve3iCJxLUh666kVTT0nZguFLdY99tvGipH9nBS7SPLLVHd8HuaKswxOYzkgJDdcLrRuF0+gZIt5FEjCSZEgraHb5+r7oE=</Signature>
  <ItineraryPriceRequest>
    <PriceItineraryBy>JourneyBySellKey</PriceItineraryBy>
    <SellByKeyRequest>
      <ActionStatusCode>LL</ActionStatusCode>
      <JourneySellKeys>
        <SellKeyList>
          <JourneySellKey>SG~ 144~ ~~DEL~01/31/2018 16:40~GOI~01/31/2018 19:25~</JourneySellKey>
          <FareSellKey>0~Z~~ZSOD~9922~~6~X</FareSellKey>
        </SellKeyList>
      </JourneySellKeys>
      <PaxPriceType>
        <PaxPriceType>
          <PaxType>ADT</PaxType>
          <PaxDiscountCode />
        </PaxPriceType>
      </PaxPriceType>
      <CurrencyCode>INR</CurrencyCode>
      <PaxCount>1</PaxCount>
      <LoyaltyFilter>MonetaryOnly</LoyaltyFilter>
      <IsAllotmentMarketFare>false</IsAllotmentMarketFare>
      <PreventOverLap>false</PreventOverLap>
    </SellByKeyRequest>
  </ItineraryPriceRequest>
</PriceItineraryRequest>