<?xml version="1.0" encoding="utf-8"?>
<PriceItineraryRequest xmlns:xsi="http://www.w3.org/2001/XMLSchema-instance" xmlns:xsd="http://www.w3.org/2001/XMLSchema">
  <ContractVersion>0</ContractVersion>
  <Signature>rezXg+pgU5Q=|iK0gPV0MPHO0Ze4d79a8G6f/DjLMRqu35ldUVRZ/pXukyz1PdSdvtDaneZnBpmBt7Cggl0BmQchJB0Oisjqk7Y8Vcnba8jhY8CmHIXVFoIHnLaOLq6qmFuH1KvxZ3RCVJ1+7BESjdgg=</Signature>
  <ItineraryPriceRequest>
    <PriceItineraryBy>JourneyBySellKey</PriceItineraryBy>
    <SellByKeyRequest>
      <ActionStatusCode>LL</ActionStatusCode>
      <JourneySellKeys>
        <SellKeyList>
          <JourneySellKey>SG~ 937~ ~~DEL~02/13/2018 10:25~SXR~02/13/2018 12:55~IXJ</JourneySellKey>
          <FareSellKey>0~Z~~ZSOD~9922~~12~X</FareSellKey>
        </SellKeyList>
      </JourneySellKeys>
      <PaxPriceType>
        <PaxPriceType>
          <PaxType>ADT</PaxType>
          <PaxDiscountCode />
        </PaxPriceType>
      </PaxPriceType>
      <CurrencyCode>INR</CurrencyCode>
      <PaxCount>1</PaxCount>
      <LoyaltyFilter>MonetaryOnly</LoyaltyFilter>
      <IsAllotmentMarketFare>false</IsAllotmentMarketFare>
      <PreventOverLap>false</PreventOverLap>
    </SellByKeyRequest>
  </ItineraryPriceRequest>
</PriceItineraryRequest>