<?xml version="1.0" encoding="utf-8"?>
<SellRequest xmlns:xsi="http://www.w3.org/2001/XMLSchema-instance" xmlns:xsd="http://www.w3.org/2001/XMLSchema">
  <ContractVersion>0</ContractVersion>
  <Signature>aoDhYR5NBgs=|N+9m1e9DbduNBLd31PKWqSKgpgfX3jGbWOxD/ZQqM+kJdZQTte/EsN0zn+ZZhSWx14nY7fN+GZ24/W4aB+1+Sf4ic5cm1LrGAwl28RVsQLMaK9EcAOW6k5NqptKhNY0zUvVoo9qlffk=</Signature>
  <SellRequestData>
    <SellBy>JourneyBySellKey</SellBy>
    <SellJourneyByKeyRequest>
      <SellJourneyByKeyRequestData>
        <ActionStatusCode>LL</ActionStatusCode>
        <JourneySellKeys>
          <SellKeyList>
            <JourneySellKey>SG~2328~ ~~DED~07/20/2019 19:30~DEL~07/20/2019 20:30~~</JourneySellKey>
            <FareSellKey>0~Z~ ~SG~ZSOD~9922~~0~8~~X</FareSellKey>
            <StandbyPriorityCode>NR</StandbyPriorityCode>
          </SellKeyList>
        </JourneySellKeys>
        <PaxPriceType>
          <PaxPriceType>
            <PaxType>ADT</PaxType>
            <PaxDiscountCode />
          </PaxPriceType>
          <PaxPriceType>
            <PaxType>ADT</PaxType>
            <PaxDiscountCode />
          </PaxPriceType>
        </PaxPriceType>
        <CurrencyCode>INR</CurrencyCode>
        <SourcePOS>
          <State>New</State>
          <DomainCode>WWW</DomainCode>
          <LocationCode>WWW</LocationCode>
        </SourcePOS>
        <PaxCount>2</PaxCount>
        <LoyaltyFilter>MonetaryOnly</LoyaltyFilter>
        <IsAllotmentMarketFare>false</IsAllotmentMarketFare>
        <PreventOverLap>false</PreventOverLap>
      </SellJourneyByKeyRequestData>
    </SellJourneyByKeyRequest>
  </SellRequestData>
</SellRequest>